{
  "lookup": {
    "rules": {
      "[{\"prev_action\": {\"action_name\": \"action_listen\"}, \"user\": {\"intent\": \"goodbye\"}}]": "utter_goodbye",
      "[{\"prev_action\": {\"action_name\": \"action_listen\"}, \"user\": {\"intent\": \"goodbye\"}}, {\"prev_action\": {\"action_name\": \"utter_goodbye\"}, \"user\": {\"intent\": \"goodbye\"}}]": "action_listen",
      "[{\"prev_action\": {\"action_name\": \"action_listen\"}, \"user\": {\"intent\": \"company_values\"}}]": "utter_company_values",
      "[{\"prev_action\": {\"action_name\": \"action_listen\"}, \"user\": {\"intent\": \"company_values\"}}, {\"prev_action\": {\"action_name\": \"utter_company_values\"}, \"user\": {\"intent\": \"company_values\"}}]": "action_listen",
      "[{\"active_loop\": {\"name\": \"should_not_be_set\"}, \"prev_action\": {\"action_name\": \"reclamation_form\"}}]": "action_submit_reclamation",
      "[{\"active_loop\": {\"name\": \"should_not_be_set\"}, \"prev_action\": {\"action_name\": \"reclamation_form\"}}, {\"active_loop\": {\"name\": \"should_not_be_set\"}, \"prev_action\": {\"action_name\": \"action_submit_reclamation\"}}]": "utter_goodbye",
      "[{\"active_loop\": {\"name\": \"should_not_be_set\"}, \"prev_action\": {\"action_name\": \"reclamation_form\"}}, {\"active_loop\": {\"name\": \"should_not_be_set\"}, \"prev_action\": {\"action_name\": \"action_submit_reclamation\"}}, {\"active_loop\": {\"name\": \"should_not_be_set\"}, \"prev_action\": {\"action_name\": \"utter_goodbye\"}}]": "action_listen",
      "[{\"prev_action\": {\"action_name\": \"action_listen\"}, \"user\": {\"intent\": \"track_reclamation\"}}]": "utter_ask_track_reclamation",
      "[{\"prev_action\": {\"action_name\": \"action_listen\"}, \"user\": {\"intent\": \"track_reclamation\"}}, {\"prev_action\": {\"action_name\": \"utter_ask_track_reclamation\"}, \"user\": {\"intent\": \"track_reclamation\"}}]": "track_reclamation_form",
      "[{\"prev_action\": {\"action_name\": \"action_listen\"}, \"user\": {\"intent\": \"track_reclamation\"}}, {\"prev_action\": {\"action_name\": \"utter_ask_track_reclamation\"}, \"user\": {\"intent\": \"track_reclamation\"}}, {\"active_loop\": {\"name\": \"track_reclamation_form\"}, \"prev_action\": {\"action_name\": \"track_reclamation_form\"}, \"user\": {\"intent\": \"track_reclamation\"}}]": "action_listen",
      "[{\"prev_action\": {\"action_name\": \"action_listen\"}, \"user\": {\"intent\": \"company_contact\"}}]": "utter_contact",
      "[{\"prev_action\": {\"action_name\": \"action_listen\"}, \"user\": {\"intent\": \"company_contact\"}}, {\"prev_action\": {\"action_name\": \"utter_contact\"}, \"user\": {\"intent\": \"company_contact\"}}]": "action_listen",
      "[{\"prev_action\": {\"action_name\": \"action_listen\"}, \"user\": {\"intent\": \"report_issue\"}}]": "utter_ask_for_details",
      "[{\"prev_action\": {\"action_name\": \"action_listen\"}, \"user\": {\"intent\": \"report_issue\"}}, {\"prev_action\": {\"action_name\": \"utter_ask_for_details\"}, \"user\": {\"intent\": \"report_issue\"}}]": "action_listen",
      "[{\"prev_action\": {\"action_name\": \"action_listen\"}, \"user\": {\"intent\": \"company_mission\"}}]": "utter_company_mission",
      "[{\"prev_action\": {\"action_name\": \"action_listen\"}, \"user\": {\"intent\": \"company_mission\"}}, {\"prev_action\": {\"action_name\": \"utter_company_mission\"}, \"user\": {\"intent\": \"company_mission\"}}]": "action_listen",
      "[{\"prev_action\": {\"action_name\": \"action_listen\"}, \"user\": {\"intent\": \"company_history\"}}]": "utter_company_history",
      "[{\"prev_action\": {\"action_name\": \"action_listen\"}, \"user\": {\"intent\": \"company_history\"}}, {\"prev_action\": {\"action_name\": \"utter_company_history\"}, \"user\": {\"intent\": \"company_history\"}}]": "action_listen",
      "[{\"prev_action\": {\"action_name\": \"action_listen\"}, \"user\": {\"intent\": \"product_support\"}}]": "utter_product_support",
      "[{\"prev_action\": {\"action_name\": \"action_listen\"}, \"user\": {\"intent\": \"product_support\"}}, {\"prev_action\": {\"action_name\": \"utter_product_support\"}, \"user\": {\"intent\": \"product_support\"}}]": "action_listen",
      "[{\"prev_action\": {\"action_name\": \"action_listen\"}, \"user\": {\"intent\": \"system_security_questions\"}}]": "utter_system_security_questions",
      "[{\"prev_action\": {\"action_name\": \"action_listen\"}, \"user\": {\"intent\": \"system_security_questions\"}}, {\"prev_action\": {\"action_name\": \"utter_system_security_questions\"}, \"user\": {\"intent\": \"system_security_questions\"}}]": "action_listen",
      "[{\"prev_action\": {\"action_name\": \"action_listen\"}, \"user\": {\"intent\": \"company_services\"}}]": "utter_company_services",
      "[{\"prev_action\": {\"action_name\": \"action_listen\"}, \"user\": {\"intent\": \"company_services\"}}, {\"prev_action\": {\"action_name\": \"utter_company_services\"}, \"user\": {\"intent\": \"company_services\"}}]": "action_listen",
      "[{\"active_loop\": {\"name\": \"should_not_be_set\"}, \"prev_action\": {\"action_name\": \"track_reclamation_form\"}}]": "action_track_reclamation",
      "[{\"active_loop\": {\"name\": \"should_not_be_set\"}, \"prev_action\": {\"action_name\": \"track_reclamation_form\"}}, {\"active_loop\": {\"name\": \"should_not_be_set\"}, \"prev_action\": {\"action_name\": \"action_track_reclamation\"}}]": "action_listen",
      "[{\"prev_action\": {\"action_name\": \"action_listen\"}, \"user\": {\"intent\": \"ask_company_info\"}}]": "utter_company_info",
      "[{\"prev_action\": {\"action_name\": \"action_listen\"}, \"user\": {\"intent\": \"ask_company_info\"}}, {\"prev_action\": {\"action_name\": \"utter_company_info\"}, \"user\": {\"intent\": \"ask_company_info\"}}]": "action_listen",
      "[{\"prev_action\": {\"action_name\": \"action_listen\"}, \"slots\": {\"reclamation_message\": [1.0]}, \"user\": {\"intent\": \"problem_description\"}}]": "utter_ask_username",
      "[{\"prev_action\": {\"action_name\": \"action_listen\"}, \"slots\": {\"reclamation_message\": [1.0]}, \"user\": {\"intent\": \"problem_description\"}}, {\"prev_action\": {\"action_name\": \"utter_ask_username\"}, \"slots\": {\"reclamation_message\": [1.0]}, \"user\": {\"intent\": \"problem_description\"}}]": "action_listen"
    },
    "rule_only_slots": [],
    "rule_only_loops": [
      "track_reclamation_form",
      "reclamation_form"
    ],
    "rules_for_loop_unhappy_path": {
      "[{\"prev_action\": {\"action_name\": \"utter_ask_track_reclamation\"}}, {\"active_loop\": {\"name\": \"track_reclamation_form\"}, \"prev_action\": {\"action_name\": \"track_reclamation_form\"}, \"user\": {\"intent\": \"track_reclamation\"}}]": "do_not_predict_loop_action"
    },
    "rules_not_in_stories": [
      "handling active loops and forms - reclamation_form - action_listen",
      "predicting default action with intent session_start",
      "predicting default action with intent back",
      "handling active loops and forms - track_reclamation_form - action_listen",
      "handling active loops and forms - reclamation_form",
      "[{\"prev_action\": {\"action_name\": \"action_listen\"}, \"user\": {\"intent\": \"goodbye\"}}, {\"prev_action\": {\"action_name\": \"utter_goodbye\"}, \"user\": {\"intent\": \"goodbye\"}}]",
      "[{\"prev_action\": {\"action_name\": \"action_listen\"}, \"user\": {\"intent\": \"goodbye\"}}]",
      "handling active loops and forms - track_reclamation_form",
      "predicting default action with intent restart"
    ]
  }
}